{
  "date": "2024-03-21",
  "indices": [
    {
      "code": "sh000001",
      "name": "上证指数",
      "date": "2024-03-21",
      "open": 3084.412,
      "close": 3077.113,
      "high": 3090.051,
      "low": 3069.272,
      "change_pct": -0.08
    },
    {
      "code": "sz399001",
      "name": "深证成指",
      "date": "2024-03-21",
      "open": 9736.231,
      "close": 9682.51,
      "high": 9758.335,
      "low": 9663.485,
      "change_pct": -0.36
    },
    {
      "code": "sz399006",
      "name": "创业板指",
      "date": "2024-03-21",
      "open": 1912.809,
      "close": 1897.094,
      "high": 1920.554,
      "low": 1897.047,
      "change_pct": -0.64
    },
    {
      "code": "sh000688",
      "name": "科创50",
      "date": "2024-03-21",
      "open": 820.143,
      "close": 806.138,
      "high": 823.28,
      "low": 805.949,
      "change_pct": -0.97
    }
  ],
  "funds": [
    {
      "code": "003096",
      "name": "中欧医疗健康混合C",
      "nav": 1.5904,
      "nav_date": "2024-03-21",
      "change_pct": -0.75,
      "avg_cost": 2.7549,
      "pnl_pct": -42.27,
      "shares": 4355.87,
      "is_qdii": false
    },
    {
      "code": "011103",
      "name": "天弘中证光伏产业指数C",
      "nav": 0.7356,
      "nav_date": "2024-03-21",
      "change_pct": -1.53,
      "avg_cost": 1.1441,
      "pnl_pct": -35.7,
      "shares": 4807.45,
      "is_qdii": false
    },
    {
      "code": "013188",
      "name": "华夏能源革新股票C",
      "nav": 2.369,
      "nav_date": "2024-03-21",
      "change_pct": -0.55,
      "avg_cost": 3.3254,
      "pnl_pct": -28.76,
      "shares": 902.15,
      "is_qdii": false
    },
    {
      "code": "118001",
      "name": "易方达亚洲精选股票(QDII)",
      "nav": 0.997,
      "nav_date": "2024-03-21",
      "change_pct": 0.81,
      "avg_cost": 1.158,
      "pnl_pct": -13.9,
      "shares": 1724.36,
      "is_qdii": true
    },
    {
      "code": "015945",
      "name": "易方达国防军工混合C",
      "nav": 1.249,
      "nav_date": "2024-03-21",
      "change_pct": -0.16,
      "avg_cost": 1.509,
      "pnl_pct": -17.23,
      "shares": 1325.38,
      "is_qdii": false
    },
    {
      "code": "161725",
      "name": "招商中证白酒指数(LOF)A",
      "nav": 0.9798,
      "nav_date": "2024-03-21",
      "change_pct": 0.43,
      "avg_cost": 1.0316,
      "pnl_pct": -5.02,
      "shares": 3128.43,
      "is_qdii": false
    }
  ],
  "total_pnl_pct": -31.32
}