{
  "date": "2025-08-26",
  "indices": [
    {
      "code": "sh000001",
      "name": "上证指数",
      "date": "2025-08-26",
      "open": 3871.471,
      "close": 3868.382,
      "high": 3888.599,
      "low": 3859.758,
      "change_pct": -0.39
    },
    {
      "code": "sz399001",
      "name": "深证成指",
      "date": "2025-08-26",
      "open": 12398.813,
      "close": 12473.174,
      "high": 12561.492,
      "low": 12361.489,
      "change_pct": 0.26
    },
    {
      "code": "sz399006",
      "name": "创业板指",
      "date": "2025-08-26",
      "open": 2747.107,
      "close": 2742.127,
      "high": 2773.24,
      "low": 2726.724,
      "change_pct": -0.76
    },
    {
      "code": "sh000688",
      "name": "科创50",
      "date": "2025-08-26",
      "open": 1266.586,
      "close": 1270.871,
      "high": 1284.073,
      "low": 1257.444,
      "change_pct": -1.31
    }
  ],
  "funds": [
    {
      "code": "003096",
      "name": "中欧医疗健康混合C",
      "nav": 1.9273,
      "nav_date": "2025-08-26",
      "change_pct": -2.06,
      "avg_cost": 2.7549,
      "pnl_pct": -30.04,
      "shares": 4355.87,
      "is_qdii": false
    },
    {
      "code": "011103",
      "name": "天弘中证光伏产业指数C",
      "nav": 0.6949,
      "nav_date": "2025-08-26",
      "change_pct": -0.64,
      "avg_cost": 1.1441,
      "pnl_pct": -39.26,
      "shares": 4807.45,
      "is_qdii": false
    },
    {
      "code": "013188",
      "name": "华夏能源革新股票C",
      "nav": 2.487,
      "nav_date": "2025-08-26",
      "change_pct": -0.36,
      "avg_cost": 3.3254,
      "pnl_pct": -25.21,
      "shares": 902.15,
      "is_qdii": false
    },
    {
      "code": "118001",
      "name": "易方达亚洲精选股票(QDII)",
      "nav": 1.212,
      "nav_date": "2025-08-26",
      "change_pct": -0.25,
      "avg_cost": 1.158,
      "pnl_pct": 4.66,
      "shares": 1724.36,
      "is_qdii": true
    },
    {
      "code": "015945",
      "name": "易方达国防军工混合C",
      "nav": 1.546,
      "nav_date": "2025-08-26",
      "change_pct": -0.96,
      "avg_cost": 1.509,
      "pnl_pct": 2.45,
      "shares": 1325.38,
      "is_qdii": false
    },
    {
      "code": "161725",
      "name": "招商中证白酒指数(LOF)A",
      "nav": 0.8389,
      "nav_date": "2025-08-26",
      "change_pct": 0.26,
      "avg_cost": 1.0316,
      "pnl_pct": -18.68,
      "shares": 3128.43,
      "is_qdii": false
    }
  ],
  "total_pnl_pct": -25.18
}