{
  "date": "2025-06-12",
  "indices": [
    {
      "code": "sh000001",
      "name": "上证指数",
      "date": "2025-06-12",
      "open": 3397.972,
      "close": 3402.658,
      "high": 3408.205,
      "low": 3388.866,
      "change_pct": 0.01
    },
    {
      "code": "sz399001",
      "name": "深证成指",
      "date": "2025-06-12",
      "open": 10208.298,
      "close": 10234.335,
      "high": 10263.463,
      "low": 10182.413,
      "change_pct": -0.11
    },
    {
      "code": "sz399006",
      "name": "创业板指",
      "date": "2025-06-12",
      "open": 2057.196,
      "close": 2067.154,
      "high": 2076.838,
      "low": 2051.24,
      "change_pct": 0.26
    },
    {
      "code": "sh000688",
      "name": "科创50",
      "date": "2025-06-12",
      "open": 978.686,
      "close": 977.973,
      "high": 982.125,
      "low": 974.629,
      "change_pct": -0.3
    }
  ],
  "funds": [
    {
      "code": "003096",
      "name": "中欧医疗健康混合C",
      "nav": 1.7233,
      "nav_date": "2025-06-12",
      "change_pct": 2.72,
      "avg_cost": 2.7549,
      "pnl_pct": -37.45,
      "shares": 4355.87,
      "is_qdii": false
    },
    {
      "code": "011103",
      "name": "天弘中证光伏产业指数C",
      "nav": 0.5596,
      "nav_date": "2025-06-12",
      "change_pct": -0.3,
      "avg_cost": 1.1441,
      "pnl_pct": -51.09,
      "shares": 4807.45,
      "is_qdii": false
    },
    {
      "code": "013188",
      "name": "华夏能源革新股票C",
      "nav": 2.154,
      "nav_date": "2025-06-12",
      "change_pct": 0.05,
      "avg_cost": 3.3254,
      "pnl_pct": -35.23,
      "shares": 902.15,
      "is_qdii": false
    },
    {
      "code": "118001",
      "name": "易方达亚洲精选股票(QDII)",
      "nav": 1.146,
      "nav_date": "2025-06-12",
      "change_pct": -0.69,
      "avg_cost": 1.158,
      "pnl_pct": -1.04,
      "shares": 1724.36,
      "is_qdii": true
    },
    {
      "code": "015945",
      "name": "易方达国防军工混合C",
      "nav": 1.314,
      "nav_date": "2025-06-12",
      "change_pct": -0.76,
      "avg_cost": 1.509,
      "pnl_pct": -12.92,
      "shares": 1325.38,
      "is_qdii": false
    },
    {
      "code": "161725",
      "name": "招商中证白酒指数(LOF)A",
      "nav": 0.7261,
      "nav_date": "2025-06-12",
      "change_pct": -1.53,
      "avg_cost": 1.0316,
      "pnl_pct": -29.62,
      "shares": 3128.43,
      "is_qdii": false
    }
  ],
  "total_pnl_pct": -34.61
}